Metadata-Version: 2.1
Name: tgs12
Version: 0.1.0
Summary: Second tea package
Home-page: https://github.com/ganisacik/tgs12
Author: ganisacik
Author-email: senin-email@example.com
License: UNKNOWN
Project-URL: Source, https://github.com/ganisacik/tgs12
Platform: UNKNOWN
